rostaing/__init__.py
rostaing/stats.py
rostaing_report-0.2.0.dist-info/licenses/LICENSE
rostaing_report-0.2.0.dist-info/METADATA
rostaing_report-0.2.0.dist-info/WHEEL
rostaing_report-0.2.0.dist-info/top_level.txt
rostaing_report-0.2.0.dist-info/RECORD
