Metadata-Version: 2.4
Name: rostaing-report
Version: 0.2.0
Summary: A comprehensive Python package for Exploratory Data Analysis (EDA), advanced statistical testing, and interactive data visualization with Plotly.
Author-email: Davila Rostaing <rostaingdavila@gmail.com>
Project-URL: Homepage, https://github.com/Rostaing/rostaing-report
Project-URL: Bug Tracker, https://github.com/Rostaing/rostaing-report/issues
Classifier: Programming Language :: Python :: 3
Classifier: License :: OSI Approved :: MIT License
Classifier: Operating System :: OS Independent
Classifier: Intended Audience :: Developers
Classifier: Intended Audience :: Science/Research
Classifier: Topic :: Scientific/Engineering
Classifier: Topic :: Scientific/Engineering :: Visualization
Requires-Python: >=3.8
License-File: LICENSE
Requires-Dist: pandas>=1.5.0
Requires-Dist: numpy>=1.23.0
Requires-Dist: scipy>=1.9.0
Requires-Dist: tabulate>=0.9.0
Requires-Dist: statsmodels>=0.13.0
Requires-Dist: pingouin>=0.5.0
Requires-Dist: scikit-learn>=1.0
Requires-Dist: lifelines>=0.27.0
Requires-Dist: plotly>=5.10.0
Requires-Dist: matplotlib>=3.5.0
Dynamic: license-file
